phoenix_apollo_sdk/__init__.py
phoenix_apollo_sdk/client.py
phoenix_apollo_client-0.0.1.dist-info/METADATA
phoenix_apollo_client-0.0.1.dist-info/WHEEL
phoenix_apollo_client-0.0.1.dist-info/top_level.txt
phoenix_apollo_client-0.0.1.dist-info/zip-safe
phoenix_apollo_client-0.0.1.dist-info/RECORD
